momepy/__init__.py
momepy/coins.py
momepy/conftest.py
momepy/dimension.py
momepy/distribution.py
momepy/diversity.py
momepy/elements.py
momepy/graph.py
momepy/intensity.py
momepy/preprocessing.py
momepy/shape.py
momepy/streetscape.py
momepy/utils.py
momepy/weights.py
momepy/datasets/__init__.py
momepy/datasets/bubenec.gpkg
momepy/datasets/nyc_graph.graphml
momepy/datasets/tests.gpkg
momepy/functional/__init__.py
momepy/functional/_dimension.py
momepy/functional/_distribution.py
momepy/functional/_diversity.py
momepy/functional/_elements.py
momepy/functional/_intensity.py
momepy/functional/_shape.py
momepy/functional/tests/__init__.py
momepy/functional/tests/conftest.py
momepy/functional/tests/test_dimension.py
momepy/functional/tests/test_distribution.py
momepy/functional/tests/test_diversity.py
momepy/functional/tests/test_elements.py
momepy/functional/tests/test_intensity.py
momepy/functional/tests/test_shape.py
momepy/tests/__init__.py
momepy/tests/test_coins.py
momepy/tests/test_dimension.py
momepy/tests/test_distribution.py
momepy/tests/test_diversity.py
momepy/tests/test_elements.py
momepy/tests/test_graph.py
momepy/tests/test_intensity.py
momepy/tests/test_preprocess.py
momepy/tests/test_shape.py
momepy/tests/test_streetscape.py
momepy/tests/test_utils.py
momepy/tests/test_weights.py
momepy-0.9.1.dist-info/LICENSE
momepy-0.9.1.dist-info/METADATA
momepy-0.9.1.dist-info/WHEEL
momepy-0.9.1.dist-info/top_level.txt
momepy-0.9.1.dist-info/RECORD
