Metadata-Version: 2.1
Name: momepy
Version: 0.9.1
Summary: Urban Morphology Measuring Toolkit
Author-email: Martin Fleischmann <martin@martinfleischmann.net>
Maintainer: momepy contributors
License: BSD 3-Clause
Project-URL: Home, http://momepy.org
Project-URL: Repository, https://github.com/pysal/momepy
Keywords: urban morphology,urban morphometrics,tessellation
Classifier: Programming Language :: Python :: 3
Classifier: License :: OSI Approved :: BSD License
Classifier: Operating System :: OS Independent
Classifier: Intended Audience :: Science/Research
Classifier: Topic :: Scientific/Engineering :: GIS
Requires-Python: >=3.10
License-File: LICENSE
Requires-Dist: geopandas>=0.12.0
Requires-Dist: libpysal>=4.12.0
Requires-Dist: networkx>=2.8
Requires-Dist: packaging
Requires-Dist: pandas>=1.5.1
Requires-Dist: shapely>=2
Requires-Dist: tqdm>=4.63.0
Provides-Extra: plus
Requires-Dist: numba; extra == "plus"
Requires-Dist: inequality; extra == "plus"
Requires-Dist: mapclassify; extra == "plus"
Requires-Dist: esda; extra == "plus"
